setup.py
api/__init__.py
api/registry.py
api/wsgi.py
api/compute/__init__.py
api/compute/compute_resource.py
api/compute/openstack.py
api/compute/templates.py
api/extensions/__init__.py
api/extensions/occi_future.py
api/extensions/openstack.py
api/network/__init__.py
api/network/networklink.py
api/network/networkresource.py
api/storage/__init__.py
api/storage/storagelink.py
api/storage/storageresource.py
nova_glue/__init__.py
nova_glue/net.py
nova_glue/security.py
nova_glue/vm.py
nova_glue/vol.py
openstackocci.egg-info/PKG-INFO
openstackocci.egg-info/SOURCES.txt
openstackocci.egg-info/dependency_links.txt
openstackocci.egg-info/entry_points.txt
openstackocci.egg-info/not-zip-safe
openstackocci.egg-info/requires.txt
openstackocci.egg-info/top_level.txt