Metadata-Version: 1.1
Name: openstackocci
Version: essex-1.1
Summary: OCCI interface for Openstack.
Home-page: http://intel.com
Author: Intel Performance Learning Solutions Ltd.
Author-email: thijsx.metsch@intel.com
License: Apache License, Version 2.0
Platform: UNKNOWN
Classifier: Programming Language :: Python
Classifier: Development Status :: 5 - Production/Stable
Classifier: Topic :: Internet :: WWW/HTTP :: WSGI :: Application
